app.py
singbox-1.0.0.dist-info/licenses/LICENSE
singbox-1.0.0.dist-info/METADATA
singbox-1.0.0.dist-info/WHEEL
singbox-1.0.0.dist-info/entry_points.txt
singbox-1.0.0.dist-info/top_level.txt
singbox-1.0.0.dist-info/RECORD
